{
  "project_info": {
    "project_number": "944608442870",
    "project_id": "seda-medical-mobile-app",
    "storage_bucket": "seda-medical-mobile-app.appspot.com"
  },
  "client": [
    {
      "client_info": {
        "mobilesdk_app_id": "1:944608442870:android:ace2a714c3ff16cd792fd7",
        "android_client_info": {
          "package_name": "com.example.seda"
        }
      },
      "oauth_client": [
        {
          "client_id": "944608442870-2fkfdnten4ncm7l992ur9ocqq66a0cau.apps.googleusercontent.com",
          "client_type": 3
        }
      ],
      "api_key": [
        {
          "current_key": "AIzaSyA8kFnFhL_5G4a4zlYzwPBI9bpKB1h-h88"
        }
      ],
      "services": {
        "appinvite_service": {
          "other_platform_oauth_client": [
            {
              "client_id": "944608442870-2fkfdnten4ncm7l992ur9ocqq66a0cau.apps.googleusercontent.com",
              "client_type": 3
            }
          ]
        }
      }
    }
  ],
  "configuration_version": "1"
}